dulli/__init__.py
dulli/dulli.py
dulliABCD-1.1.1.dist-info/METADATA
dulliABCD-1.1.1.dist-info/WHEEL
dulliABCD-1.1.1.dist-info/top_level.txt
dulliABCD-1.1.1.dist-info/RECORD
