Metadata-Version: 2.1
Name: dulliABCD
Version: 1.1.1
Summary: dulli haha sussy baka
Home-page: UNKNOWN
Author: joe
Author-email: <sussybakayourmomthiccboi1234@gmail.com>
License: UNKNOWN
Keywords: python,dulli,sus,thicc,python go brrrrrrrrrr
Platform: UNKNOWN
